Metadata-Version: 2.1
Name: Velocidade
Version: 1.0
Summary: esse pacote não faz absolutamente nada
Author: KLenine
Author-email: nono@gmail.com
Keywords: nem,pilha,nisso
License-File: license.txt
